[{"_path":"/blog/choosing-the-right-lead-reduction-filter","_dir":"blog","_draft":false,"_partial":false,"_locale":"","title":"How to Choose the Right Lead Reduction Filter for Your Needs","description":"Lead in drinking water is a severe issue, especially harmful to children and pregnant women. Choosing the right lead reduction filter is crucial to ensure water safety. Here's a comprehensive guide to help you make the right decision.","_type":"markdown","_id":"content:blog:choosing-the-right-lead-reduction-filter.md","_source":"content","_file":"blog/choosing-the-right-lead-reduction-filter.md","_stem":"blog/choosing-the-right-lead-reduction-filter","_extension":"md","sitemap":{"loc":"/blog/choosing-the-right-lead-reduction-filter"}},{"_path":"/blog/comparing-alkaline-systems-ro-ultrafiltration","_dir":"blog","_draft":false,"_partial":false,"_locale":"","title":"Comparing Alkaline Systems: Reverse Osmosis, Ultrafiltration, and More","description":"In today's market, consumers looking to enhance their drinking water with alkaline systems have a range of technologies to choose from, including reverse osmosis and ultrafiltration. This article provides a detailed comparison of these systems, helping you make an informed decision based on your specific needs.","_type":"markdown","_id":"content:blog:comparing-alkaline-systems-ro-ultrafiltration.md","_source":"content","_file":"blog/comparing-alkaline-systems-ro-ultrafiltration.md","_stem":"blog/comparing-alkaline-systems-ro-ultrafiltration","_extension":"md","sitemap":{"loc":"/blog/comparing-alkaline-systems-ro-ultrafiltration"}}]